pmp/__init__.py
pmp/_common/__init__.py
pmp/_common/intro.py
pmp/_common/methods.py
pmp/algorithms/__init__.py
pmp/algorithms/greedy.py
pmp/algorithms/rule_builder.py
pmp/experiments/__init__.py
pmp/experiments/election_config.py
pmp/experiments/experiment.py
pmp/experiments/experiment_config.py
pmp/experiments/generating_functions.py
pmp/experiments/helpers.py
pmp/experiments/histogram.py
pmp/experiments/saving_files.py
pmp/experiments/visualize.py
pmp/preferences/__init__.py
pmp/preferences/approval.py
pmp/preferences/ordinal.py
pmp/preferences/preference.py
pmp/preferences/profile.py
pmp/properties/__init__.py
pmp/properties/justified_representation.py
pmp/rules/__init__.py
pmp/rules/bloc.py
pmp/rules/borda.py
pmp/rules/chamberlin_courant.py
pmp/rules/pav.py
pmp/rules/rule.py
pmp/rules/sntv.py
pmp/rules/tie_breaking.py
pmp/rules/weakly_separable.py
pmp/utils/__init__.py
pmp/utils/ilp/__init__.py
pmp/utils/ilp/cplex_wrapper.py
pmp/utils/ilp/gurobi_wrapper.py
pmp/utils/ilp/ilp.py
pmp/utils/ilp/model.py
pmp/utils/ilp/solver_wrapper.py
pmp/utils/ilp/solvers.py
python_multiwinner_package-1.5.0.dist-info/LICENSE.txt
python_multiwinner_package-1.5.0.dist-info/METADATA
python_multiwinner_package-1.5.0.dist-info/WHEEL
python_multiwinner_package-1.5.0.dist-info/top_level.txt
python_multiwinner_package-1.5.0.dist-info/RECORD
